codsworth/__init__.py
codsworth/cryptodata.csv
codsworth/dimensions.json
codsworth/intents.json
codsworth/stockdata.csv
codsworth-0.1.8.dist-info/METADATA
codsworth-0.1.8.dist-info/WHEEL
codsworth-0.1.8.dist-info/entry_points.txt
codsworth-0.1.8.dist-info/top_level.txt
codsworth-0.1.8.dist-info/RECORD
